a_mem-0.2.6.dist-info/licenses/LICENSE
agentic_memory/__init__.py
agentic_memory/llm_controller.py
agentic_memory/memory_system.py
agentic_memory/retrievers.py
agentic_memory/thread_safe_cache.py
agentic_memory_mcp/__init__.py
agentic_memory_mcp/background.py
agentic_memory_mcp/config.py
agentic_memory_mcp/install_hook.py
agentic_memory_mcp/prompts.py
agentic_memory_mcp/resources.py
agentic_memory_mcp/server.py
agentic_memory_mcp/session-start.sh
agentic_memory_mcp/tools.py
agentic_memory_mcp/viz.py
agentic_memory_mcp/viz_server.py
agentic_memory_mcp/templates/graph.html
agentic_memory_mcp/templates/graph_live.html
a_mem-0.2.6.dist-info/METADATA
a_mem-0.2.6.dist-info/WHEEL
a_mem-0.2.6.dist-info/entry_points.txt
a_mem-0.2.6.dist-info/top_level.txt
a_mem-0.2.6.dist-info/RECORD
