Metadata-Version: 2.4
Name: a-mem
Version: 0.2.6
Summary: Self-evolving memory system for AI agents with semantic search and knowledge graph capabilities. Includes MCP server for Claude and other AI assistants.
License: MIT License
Project-URL: Homepage, https://github.com/DiaaAj/a-mem-mcp
Project-URL: Bug Tracker, https://github.com/DiaaAj/a-mem-mcp/issues
Project-URL: Research Paper, https://arxiv.org/pdf/2502.12110
Classifier: Programming Language :: Python :: 3
Classifier: License :: OSI Approved :: MIT License
Classifier: Operating System :: OS Independent
Classifier: Topic :: Scientific/Engineering :: Artificial Intelligence
Classifier: Development Status :: 4 - Beta
Requires-Python: >=3.8
License-File: LICENSE
Requires-Dist: sentence-transformers>=2.2.2
Requires-Dist: chromadb>=0.4.22
Requires-Dist: rank_bm25>=0.2.2
Requires-Dist: nltk>=3.8.1
Requires-Dist: litellm>=1.16.11
Requires-Dist: numpy>=1.24.3
Requires-Dist: scikit-learn>=1.3.2
Requires-Dist: openai>=1.3.7
Requires-Dist: requests>=2.31.0
Requires-Dist: mcp>=1.0.0
Requires-Dist: pydantic>=2.0.0
Requires-Dist: python-dotenv>=1.0.0
Requires-Dist: aiohttp>=3.9.0
Dynamic: license-file
